mobilenium
