Metadata-Version: 1.1
Name: mobilenium
Version: 0.0.4
Summary: Mobilenium uses BrowserMob Proxy to give superpowers to Selenium.
Home-page: https://github.com/rafpyprog/Mobilenium.git
Author: Rafael Alves Ribeiro
Author-email: rafael.alves.ribeiro@gmail.com
License: License :: OSI Approved :: MIT License
Keywords: selenium browsermob proxy
Platform: UNKNOWN
Classifier: Programming Language :: Python :: 3.5
Classifier: Programming Language :: Python :: 3.6
Classifier: License :: OSI Approved :: Apache Software License
Classifier: Development Status :: 2 - Pre-Alpha
